<?xml version="1.0" encoding="UTF-8"?>
<!DOCTYPE hibernate-mapping PUBLIC "-//Hibernate/Hibernate Mapping DTD 3.0//EN" "http://www.hibernate.org/dtd/hibernate-mapping-3.0.dtd">
<!-- Generated 07/06/2015 16:27:15 by Hibernate Tools 4.3.1 -->
<hibernate-mapping>
  <class catalog="final_visual" name="ar.edu.unju.fi.apu.dominio.hibernate.Usuarios" optimistic-lock="version" table="usuarios">
    <id name="nombreUsuario" type="string">
      <column length="8" name="nombre_usuario"/>
      <generator class="assigned"/>
    </id>
    <property name="password" type="string">
      <column length="700" name="password" not-null="true"/>
    </property>
    <property name="nombreReal" type="string">
      <column length="50" name="nombre_real" not-null="true"/>
    </property>
  </class>
</hibernate-mapping>
